{"id":"7xcamxt1pxg1hi6mao29io0","title":"Neo Democrats|新同盟","desc":"","updated":1653381075110,"created":1652205295199,"custom":{},"fname":"sites.neodem","type":"note","vault":{"fsPath":"vault"},"contentHash":"48deb28fde9a7afc7906db057326cf4e","links":[{"from":{"fname":"sites","vaultName":"vault"},"type":"backlink","position":{"start":{"line":32,"column":5,"offset":615},"end":{"line":32,"column":21,"offset":631},"indent":[]},"value":"sites.neodem","alias":"sites.neodem"}],"anchors":{"archives":{"type":"header","text":"Archives","value":"archives","line":13,"column":0,"depth":2}},"children":[],"parent":"wx39zljncctue32jn06u29u","data":{}}
