{"id":"j9qhqqamlyy1cws9l6r3ick","title":"Financier Conscience|思言財雋","desc":"","updated":1653379159126,"created":1651468552878,"custom":{},"fname":"sites.financier","type":"note","vault":{"fsPath":"vault"},"contentHash":"917823d9e9180e1d67c4cb9e4f3211aa","links":[{"from":{"fname":"sites","vaultName":"vault"},"type":"backlink","position":{"start":{"line":26,"column":5,"offset":494},"end":{"line":26,"column":24,"offset":513},"indent":[]},"value":"sites.financier","alias":"sites.financier"}],"anchors":{"archives":{"type":"header","text":"Archives","value":"archives","line":13,"column":0,"depth":2}},"children":[],"parent":"wx39zljncctue32jn06u29u","data":{}}
