{"id":"p9yv8nnjdb90urz9yk1i7f4","title":"GUHKST|​香港言語治療師總工會","desc":"","updated":1653380002165,"created":1650600081534,"custom":{},"fname":"sites.guhkst","type":"note","vault":{"fsPath":"vault"},"contentHash":"a1084838804cf3baab4eb90b18f2ad19","links":[{"type":"wiki","from":{"fname":"sites.guhkst","id":"p9yv8nnjdb90urz9yk1i7f4","vaultName":"vault"},"value":"howto.replay","alias":"howto.replay","position":{"start":{"line":13,"column":128,"offset":1397},"end":{"line":13,"column":144,"offset":1413},"indent":[]},"xvault":false,"sameFile":false,"to":{"fname":"howto.replay"}},{"from":{"fname":"sites","vaultName":"vault"},"type":"backlink","position":{"start":{"line":16,"column":5,"offset":285},"end":{"line":16,"column":21,"offset":301},"indent":[]},"value":"sites.guhkst","alias":"sites.guhkst"}],"anchors":{"archives":{"type":"header","text":"Archives","value":"archives","line":16,"column":0,"depth":2}},"children":[],"parent":"wx39zljncctue32jn06u29u","data":{}}
